scalekit_demo/__init__.py
scalekit_demo/_base_client.py
scalekit_demo/_client.py
scalekit_demo/_compat.py
scalekit_demo/_constants.py
scalekit_demo/_exceptions.py
scalekit_demo/_files.py
scalekit_demo/_models.py
scalekit_demo/_qs.py
scalekit_demo/_resource.py
scalekit_demo/_response.py
scalekit_demo/_streaming.py
scalekit_demo/_types.py
scalekit_demo/_version.py
scalekit_demo/py.typed
scalekit_demo/_utils/__init__.py
scalekit_demo/_utils/_compat.py
scalekit_demo/_utils/_datetime_parse.py
scalekit_demo/_utils/_logs.py
scalekit_demo/_utils/_proxy.py
scalekit_demo/_utils/_reflection.py
scalekit_demo/_utils/_resources_proxy.py
scalekit_demo/_utils/_streams.py
scalekit_demo/_utils/_sync.py
scalekit_demo/_utils/_transform.py
scalekit_demo/_utils/_typing.py
scalekit_demo/_utils/_utils.py
scalekit_demo/lib/.keep
scalekit_demo/resources/__init__.py
scalekit_demo/resources/migrations.py
scalekit_demo/resources/api/__init__.py
scalekit_demo/resources/api/api.py
scalekit_demo/resources/api/v1/__init__.py
scalekit_demo/resources/api/v1/auth.py
scalekit_demo/resources/api/v1/billing.py
scalekit_demo/resources/api/v1/directory_user_attributes.py
scalekit_demo/resources/api/v1/events.py
scalekit_demo/resources/api/v1/mcp.py
scalekit_demo/resources/api/v1/members.py
scalekit_demo/resources/api/v1/members_this.py
scalekit_demo/resources/api/v1/permissions.py
scalekit_demo/resources/api/v1/providers.py
scalekit_demo/resources/api/v1/scopes.py
scalekit_demo/resources/api/v1/sessions.py
scalekit_demo/resources/api/v1/sso_user_attributes.py
scalekit_demo/resources/api/v1/tools.py
scalekit_demo/resources/api/v1/totp.py
scalekit_demo/resources/api/v1/user.py
scalekit_demo/resources/api/v1/user_profile_attributes.py
scalekit_demo/resources/api/v1/v1.py
scalekit_demo/resources/api/v1/workspaces_this.py
scalekit_demo/resources/api/v1/clients/__init__.py
scalekit_demo/resources/api/v1/clients/clients.py
scalekit_demo/resources/api/v1/clients/secrets.py
scalekit_demo-0.0.2.dist-info/METADATA
scalekit_demo-0.0.2.dist-info/WHEEL
scalekit_demo-0.0.2.dist-info/licenses/LICENSE
scalekit_demo-0.0.2.dist-info/RECORD
